{
    "Select" : [
        {
            "DSName": "customer",
            "Fields": ["fname","lname"]
        },
        {
            "DSName": "region",
            "Fields": ["rname"]
        }
    ],
    "Where":[
        {
            "Literals":[
            {
                "Value1": "customer.age",
                "Value2": "Constant::35",
                "Operator": "<="
            },
            {
                "Value1": "customer.rno",
                "Value2": "region.rnumber",
                "Operator": "="
            }
            ]
        }
    ]
}